invenio_deposit/__init__.py
invenio_deposit/acl.py
invenio_deposit/autocomplete_utils.py
invenio_deposit/bundles.py
invenio_deposit/cache.py
invenio_deposit/config.py
invenio_deposit/field_base.py
invenio_deposit/field_widgets.py
invenio_deposit/filter_utils.py
invenio_deposit/form.py
invenio_deposit/helpers.py
invenio_deposit/json_utils.py
invenio_deposit/models.py
invenio_deposit/processor_utils.py
invenio_deposit/registry.py
invenio_deposit/restful.py
invenio_deposit/signals.py
invenio_deposit/storage.py
invenio_deposit/tasks.py
invenio_deposit/url_converters.py
invenio_deposit/validation_utils.py
invenio_deposit/version.py
invenio_deposit/fields/__init__.py
invenio_deposit/fields/abstract.py
invenio_deposit/fields/author.py
invenio_deposit/fields/date.py
invenio_deposit/fields/doi.py
invenio_deposit/fields/file_upload.py
invenio_deposit/fields/issn.py
invenio_deposit/fields/jinja.py
invenio_deposit/fields/journal.py
invenio_deposit/fields/jsonfield.py
invenio_deposit/fields/keywords.py
invenio_deposit/fields/language.py
invenio_deposit/fields/notes.py
invenio_deposit/fields/pages_number.py
invenio_deposit/fields/publisher.py
invenio_deposit/fields/record_id.py
invenio_deposit/fields/title.py
invenio_deposit/fields/wtformsext.py
invenio_deposit/static/css/deposit/form.css
invenio_deposit/static/js/deposit/dynamic_field_list.js
invenio_deposit/static/js/deposit/form.js
invenio_deposit/static/js/deposit/init.js
invenio_deposit/static/js/deposit/jsonwidget.js
invenio_deposit/static/js/deposit/templates/error.mustache
invenio_deposit/static/js/deposit/templates/field_message.mustache
invenio_deposit/static/js/deposit/templates/file_entry.mustache
invenio_deposit/static/js/deposit/templates/file_link.mustache
invenio_deposit/static/js/deposit/templates/file_list_row.mustache
invenio_deposit/static/js/deposit/templates/flash_message.mustache
invenio_deposit/static/js/deposit/templates/loader.mustache
invenio_deposit-0.2.0.dist-info/top_level.txt
invenio_deposit-0.2.0.dist-info/METADATA
invenio_deposit-0.2.0.dist-info/DESCRIPTION.rst
invenio_deposit-0.2.0.dist-info/metadata.json
invenio_deposit-0.2.0.dist-info/WHEEL
invenio_deposit-0.2.0.dist-info/RECORD
