Metadata-Version: 2.0
Name: invenio-deposit
Version: 0.2.0
Summary: Invenio module for depositing metadata using workflows.
Home-page: https://github.com/inveniosoftware/invenio-deposit
Author: CERN
Author-email: info@invenio-software.org
License: GPLv2
Keywords: invenio TODO
Platform: any
Classifier: Environment :: Web Environment
Classifier: Intended Audience :: Developers
Classifier: License :: OSI Approved :: GNU General Public License v2 (GPLv2)
Classifier: Operating System :: OS Independent
Classifier: Programming Language :: Python
Classifier: Topic :: Internet :: WWW/HTTP :: Dynamic Content
Classifier: Topic :: Software Development :: Libraries :: Python Modules
Classifier: Programming Language :: Python :: 2
Classifier: Programming Language :: Python :: 2.7
Classifier: Development Status :: 1 - Planning
Requires-Dist: Flask (>=0.10.1)
Requires-Dist: six (>=1.7.2)
Requires-Dist: idutils (>=0.1.0)
Requires-Dist: invenio-access (>=0.1.0)
Requires-Dist: invenio-formatter (>=0.2.1)
Requires-Dist: invenio-knowledge (>=0.1.0)
Requires-Dist: invenio-oauth2server (>=0.1.0)
Requires-Dist: invenio-pidstore (>=0.1.0)
Requires-Dist: invenio-records (>=0.3.2)
Requires-Dist: invenio-workflows (>=0.1.1)
Provides-Extra: docs
Requires-Dist: Sphinx (>=1.3); extra == 'docs'
Requires-Dist: sphinx-rtd-theme (>=0.1.7); extra == 'docs'
Provides-Extra: jsonschema
Requires-Dist: invenio-jsonschemas (>=0.0.0); extra == 'jsonschema'
Requires-Dist: jsonschema (>=2.5.0); extra == 'jsonschema'
Provides-Extra: tests
Requires-Dist: unittest2 (>=1.1.0); extra == 'tests'
Requires-Dist: Flask-Testing (>=0.4.1); extra == 'tests'
Requires-Dist: pytest (>=2.7.0); extra == 'tests'
Requires-Dist: pytest-cov (>=1.8.0,<2.0.0); extra == 'tests'
Requires-Dist: pytest-pep8 (>=1.0.6); extra == 'tests'
Requires-Dist: coverage (>=3.7.1); extra == 'tests'
Requires-Dist: invenio-jsonschemas (>=0.0.0); extra == 'tests'
Requires-Dist: jsonschema (>=2.5.0); extra == 'tests'
